fluentcms_forms_builder/__init__.py
fluentcms_forms_builder/admin.py
fluentcms_forms_builder/content_plugins.py
fluentcms_forms_builder/forms.py
fluentcms_forms_builder/meta.py
fluentcms_forms_builder/models.py
fluentcms_forms_builder/locale/ru/LC_MESSAGES/django.mo
fluentcms_forms_builder/locale/ru/LC_MESSAGES/django.po
fluentcms_forms_builder/migrations/0001_initial.py
fluentcms_forms_builder/migrations/0002_auto_20160708_1024.py
fluentcms_forms_builder/migrations/__init__.py
fluentcms_forms_builder/templates/fluentcms_forms_builder/form.html
fluentcms_forms_builder/templates/fluentcms_forms_builder/form_sent.html
fluentcms_forms_builder/templates/fluentcms_forms_builder/includes/built_form.html
fluentcms_forms_builder/tests/__init__.py
fluentcms_forms_builder/tests/test_all.py
fluentcms_forms_builder/tests/urls.py
fluentcms_forms_builder-2.0.1.dist-info/AUTHORS
fluentcms_forms_builder-2.0.1.dist-info/LICENSE
fluentcms_forms_builder-2.0.1.dist-info/METADATA
fluentcms_forms_builder-2.0.1.dist-info/WHEEL
fluentcms_forms_builder-2.0.1.dist-info/top_level.txt
fluentcms_forms_builder-2.0.1.dist-info/RECORD
