Metadata-Version: 2.1
Name: fluentcms-forms-builder
Version: 2.0.1
Summary: A django-forms-builder plugin for django-fluent-pages
Home-page: https://github.com/bashu/fluentcms-forms-builder/
Author: Basil Shubin
Author-email: basil.shubin@gmail.com
License: Apache License, Version 2
Download-URL: https://github.com/bashu/fluentcms-forms-builder/zipball/master
Platform: UNKNOWN
Classifier: Development Status :: 5 - Production/Stable
Classifier: Environment :: Web Environment
Classifier: Intended Audience :: Developers
Classifier: License :: OSI Approved :: Apache Software License
Classifier: Operating System :: OS Independent
Classifier: Programming Language :: Python
Classifier: Programming Language :: Python :: 3 :: Only
Classifier: Programming Language :: Python :: 3.6
Classifier: Programming Language :: Python :: 3.7
Classifier: Programming Language :: Python :: 3.8
Classifier: Programming Language :: Python :: 3.9
Classifier: Framework :: Django
Classifier: Framework :: Django :: 2.0
Classifier: Framework :: Django :: 2.1
Classifier: Framework :: Django :: 2.2
Classifier: Topic :: Internet :: WWW/HTTP
Classifier: Topic :: Internet :: WWW/HTTP :: Dynamic Content
Classifier: Topic :: Software Development :: Libraries :: Python Modules
License-File: LICENSE
License-File: AUTHORS
Requires-Dist: django-fluent-contents (>=2.0)
Requires-Dist: django-forms-builder (>0.13)
Requires-Dist: django-polymorphic (<3.0)
Requires-Dist: django-any-urlfield
Provides-Extra: develop
Requires-Dist: tox ; extra == 'develop'
Requires-Dist: django ; extra == 'develop'
Provides-Extra: test
Requires-Dist: coverage ; extra == 'test'
